sirbot/__init__.py
sirbot/__version__.py
sirbot/bot.py
sirbot/endpoints/__init__.py
sirbot/plugins/__init__.py
sirbot/plugins/apscheduler/__init__.py
sirbot/plugins/apscheduler/plugin.py
sirbot/plugins/github/__init__.py
sirbot/plugins/github/plugin.py
sirbot/plugins/postgres/__init__.py
sirbot/plugins/postgres/plugin.py
sirbot/plugins/readthedocs/__init__.py
sirbot/plugins/readthedocs/plugin.py
sirbot/plugins/slack/__init__.py
sirbot/plugins/slack/endpoints.py
sirbot/plugins/slack/plugin.py
sirbot-0.1.1.dist-info/LICENSE
sirbot-0.1.1.dist-info/WHEEL
sirbot-0.1.1.dist-info/METADATA
sirbot-0.1.1.dist-info/RECORD
